{
	"@type":"NativeView",
	"Name":"Payroll Example",
	"Columns":
	[
		{
			"Subset":
			{
				"Hierarchy":
				{
					"@id":"Dimensions('plan_Period')/Hierarchies('plan_Period')"
				},
				"Alias":"rpt_Period",
				"Elements":
				[
					{
						"@id":"Dimensions('plan_Period')/Hierarchies('plan_Period')/Elements('Year +1')"
					},
					{
						"@id":"Dimensions('plan_Period')/Hierarchies('plan_Period')/Elements('Year +1 1')"
					},
					{
						"@id":"Dimensions('plan_Period')/Hierarchies('plan_Period')/Elements('Year +1 2')"
					},
					{
						"@id":"Dimensions('plan_Period')/Hierarchies('plan_Period')/Elements('Year +1 3')"
					},
					{
						"@id":"Dimensions('plan_Period')/Hierarchies('plan_Period')/Elements('Year +1 4')"
					},
					{
						"@id":"Dimensions('plan_Period')/Hierarchies('plan_Period')/Elements('Year +1 5')"
					},
					{
						"@id":"Dimensions('plan_Period')/Hierarchies('plan_Period')/Elements('Year +1 6')"
					},
					{
						"@id":"Dimensions('plan_Period')/Hierarchies('plan_Period')/Elements('Year +1 7')"
					},
					{
						"@id":"Dimensions('plan_Period')/Hierarchies('plan_Period')/Elements('Year +1 8')"
					},
					{
						"@id":"Dimensions('plan_Period')/Hierarchies('plan_Period')/Elements('Year +1 9')"
					},
					{
						"@id":"Dimensions('plan_Period')/Hierarchies('plan_Period')/Elements('Year +1 10')"
					},
					{
						"@id":"Dimensions('plan_Period')/Hierarchies('plan_Period')/Elements('Year +1 11')"
					},
					{
						"@id":"Dimensions('plan_Period')/Hierarchies('plan_Period')/Elements('Year +1 12')"
					}
				]
			}
		}
	],
	"Rows":
	[
		{
			"Subset":
			{
				"Hierarchy":
				{
					"@id":"Dimensions('Account_PL')/Hierarchies('Account_PL')"
				},
				"Alias":"Code & Description",
				"Elements":
				[
					{
						"@id":"Dimensions('Account_PL')/Hierarchies('Account_PL')/Elements('26010')"
					},
					{
						"@id":"Dimensions('Account_PL')/Hierarchies('Account_PL')/Elements('26020')"
					},
					{
						"@id":"Dimensions('Account_PL')/Hierarchies('Account_PL')/Elements('26052')"
					},
					{
						"@id":"Dimensions('Account_PL')/Hierarchies('Account_PL')/Elements('26075')"
					},
					{
						"@id":"Dimensions('Account_PL')/Hierarchies('Account_PL')/Elements('26085')"
					},
					{
						"@id":"Dimensions('Account_PL')/Hierarchies('Account_PL')/Elements('26086')"
					},
					{
						"@id":"Dimensions('Account_PL')/Hierarchies('Account_PL')/Elements('26087')"
					},
					{
						"@id":"Dimensions('Account_PL')/Hierarchies('Account_PL')/Elements('46010')"
					},
					{
						"@id":"Dimensions('Account_PL')/Hierarchies('Account_PL')/Elements('46011')"
					},
					{
						"@id":"Dimensions('Account_PL')/Hierarchies('Account_PL')/Elements('46020')"
					},
					{
						"@id":"Dimensions('Account_PL')/Hierarchies('Account_PL')/Elements('46021')"
					},
					{
						"@id":"Dimensions('Account_PL')/Hierarchies('Account_PL')/Elements('46048')"
					},
					{
						"@id":"Dimensions('Account_PL')/Hierarchies('Account_PL')/Elements('46052')"
					},
					{
						"@id":"Dimensions('Account_PL')/Hierarchies('Account_PL')/Elements('46075')"
					},
					{
						"@id":"Dimensions('Account_PL')/Hierarchies('Account_PL')/Elements('46076')"
					},
					{
						"@id":"Dimensions('Account_PL')/Hierarchies('Account_PL')/Elements('46085')"
					},
					{
						"@id":"Dimensions('Account_PL')/Hierarchies('Account_PL')/Elements('46086')"
					},
					{
						"@id":"Dimensions('Account_PL')/Hierarchies('Account_PL')/Elements('46087')"
					},
					{
						"@id":"Dimensions('Account_PL')/Hierarchies('Account_PL')/Elements('46088')"
					},
					{
						"@id":"Dimensions('Account_PL')/Hierarchies('Account_PL')/Elements('46089')"
					},
					{
						"@id":"Dimensions('Account_PL')/Hierarchies('Account_PL')/Elements('46090')"
					}
				]
			}
		}
	],
	"Titles":
	[
		{
			"Subset":
			{
				"Hierarchy":
				{
					"@id":"Dimensions('plan_Version')/Hierarchies('plan_Version')"
				},
				"Elements":
				[
					{
						"@id":"Dimensions('plan_Version')/Hierarchies('plan_Version')/Elements('Budget')"
					},
					{
						"@id":"Dimensions('plan_Version')/Hierarchies('plan_Version')/Elements('Forecast')"
					}
				]
			},
			"Selected":
			{
				"@id":"Dimensions('plan_Version')/Hierarchies('plan_Version')/Elements('Budget')"
			}
		},
		{
			"Subset":
			{
				"Hierarchy":
				{
					"@id":"Dimensions('Currency')/Hierarchies('Currency')"
				},
				"Elements":
				[
					{
						"@id":"Dimensions('Currency')/Hierarchies('Currency')/Elements('LCY')"
					}
				]
			},
			"Selected":
			{
				"@id":"Dimensions('Currency')/Hierarchies('Currency')/Elements('LCY')"
			}
		},
		{
			"Subset":
			{
				"Hierarchy":
				{
					"@id":"Dimensions('m_plan_Profit_and_Loss')/Hierarchies('m_plan_Profit_and_Loss')"
				},
				"Elements":
				[
					{
						"@id":"Dimensions('m_plan_Profit_and_Loss')/Hierarchies('m_plan_Profit_and_Loss')/Elements('Value')"
					}
				]
			},
			"Selected":
			{
				"@id":"Dimensions('m_plan_Profit_and_Loss')/Hierarchies('m_plan_Profit_and_Loss')/Elements('Value')"
			}
		},
		{
			"Subset":
			{
				"Hierarchy":
				{
					"@id":"Dimensions('Business_Unit')/Hierarchies('Business_Unit')"
				},
				"Alias":"Code & Description",
				"Elements":
				[
					{
						"@id":"Dimensions('Business_Unit')/Hierarchies('Business_Unit')/Elements('Fletcher Steel')"
					},
					{
						"@id":"Dimensions('Business_Unit')/Hierarchies('Business_Unit')/Elements('Fletcher Steel Exc CSP')"
					},
					{
						"@id":"Dimensions('Business_Unit')/Hierarchies('Business_Unit')/Elements('Easysteel')"
					},
					{
						"@id":"Dimensions('Business_Unit')/Hierarchies('Business_Unit')/Elements('10')"
					},
					{
						"@id":"Dimensions('Business_Unit')/Hierarchies('Business_Unit')/Elements('11')"
					},
					{
						"@id":"Dimensions('Business_Unit')/Hierarchies('Business_Unit')/Elements('12')"
					},
					{
						"@id":"Dimensions('Business_Unit')/Hierarchies('Business_Unit')/Elements('14')"
					},
					{
						"@id":"Dimensions('Business_Unit')/Hierarchies('Business_Unit')/Elements('16')"
					},
					{
						"@id":"Dimensions('Business_Unit')/Hierarchies('Business_Unit')/Elements('17')"
					},
					{
						"@id":"Dimensions('Business_Unit')/Hierarchies('Business_Unit')/Elements('18')"
					},
					{
						"@id":"Dimensions('Business_Unit')/Hierarchies('Business_Unit')/Elements('19')"
					},
					{
						"@id":"Dimensions('Business_Unit')/Hierarchies('Business_Unit')/Elements('Dimond Consolidation')"
					},
					{
						"@id":"Dimensions('Business_Unit')/Hierarchies('Business_Unit')/Elements('20')"
					},
					{
						"@id":"Dimensions('Business_Unit')/Hierarchies('Business_Unit')/Elements('21')"
					},
					{
						"@id":"Dimensions('Business_Unit')/Hierarchies('Business_Unit')/Elements('23')"
					},
					{
						"@id":"Dimensions('Business_Unit')/Hierarchies('Business_Unit')/Elements('24')"
					},
					{
						"@id":"Dimensions('Business_Unit')/Hierarchies('Business_Unit')/Elements('25')"
					},
					{
						"@id":"Dimensions('Business_Unit')/Hierarchies('Business_Unit')/Elements('26')"
					},
					{
						"@id":"Dimensions('Business_Unit')/Hierarchies('Business_Unit')/Elements('27')"
					},
					{
						"@id":"Dimensions('Business_Unit')/Hierarchies('Business_Unit')/Elements('28')"
					},
					{
						"@id":"Dimensions('Business_Unit')/Hierarchies('Business_Unit')/Elements('22')"
					},
					{
						"@id":"Dimensions('Business_Unit')/Hierarchies('Business_Unit')/Elements('76')"
					},
					{
						"@id":"Dimensions('Business_Unit')/Hierarchies('Business_Unit')/Elements('29')"
					},
					{
						"@id":"Dimensions('Business_Unit')/Hierarchies('Business_Unit')/Elements('PCC')"
					},
					{
						"@id":"Dimensions('Business_Unit')/Hierarchies('Business_Unit')/Elements('30')"
					},
					{
						"@id":"Dimensions('Business_Unit')/Hierarchies('Business_Unit')/Elements('41')"
					},
					{
						"@id":"Dimensions('Business_Unit')/Hierarchies('Business_Unit')/Elements('42')"
					},
					{
						"@id":"Dimensions('Business_Unit')/Hierarchies('Business_Unit')/Elements('43')"
					},
					{
						"@id":"Dimensions('Business_Unit')/Hierarchies('Business_Unit')/Elements('44')"
					},
					{
						"@id":"Dimensions('Business_Unit')/Hierarchies('Business_Unit')/Elements('Reinforcing')"
					},
					{
						"@id":"Dimensions('Business_Unit')/Hierarchies('Business_Unit')/Elements('50')"
					},
					{
						"@id":"Dimensions('Business_Unit')/Hierarchies('Business_Unit')/Elements('51')"
					},
					{
						"@id":"Dimensions('Business_Unit')/Hierarchies('Business_Unit')/Elements('52')"
					},
					{
						"@id":"Dimensions('Business_Unit')/Hierarchies('Business_Unit')/Elements('53')"
					},
					{
						"@id":"Dimensions('Business_Unit')/Hierarchies('Business_Unit')/Elements('59')"
					},
					{
						"@id":"Dimensions('Business_Unit')/Hierarchies('Business_Unit')/Elements('SD Support')"
					},
					{
						"@id":"Dimensions('Business_Unit')/Hierarchies('Business_Unit')/Elements('97')"
					},
					{
						"@id":"Dimensions('Business_Unit')/Hierarchies('Business_Unit')/Elements('98')"
					},
					{
						"@id":"Dimensions('Business_Unit')/Hierarchies('Business_Unit')/Elements('99')"
					},
					{
						"@id":"Dimensions('Business_Unit')/Hierarchies('Business_Unit')/Elements('94')"
					},
					{
						"@id":"Dimensions('Business_Unit')/Hierarchies('Business_Unit')/Elements('NZSD Divisional')"
					},
					{
						"@id":"Dimensions('Business_Unit')/Hierarchies('Business_Unit')/Elements('70')"
					},
					{
						"@id":"Dimensions('Business_Unit')/Hierarchies('Business_Unit')/Elements('CSP Pacific')"
					},
					{
						"@id":"Dimensions('Business_Unit')/Hierarchies('Business_Unit')/Elements('34')"
					}
				]
			},
			"Selected":
			{
				"@id":"Dimensions('Business_Unit')/Hierarchies('Business_Unit')/Elements('Fletcher Steel')"
			}
		},
		{
			"Subset":
			{
				"@id":"Dimensions('Branch')/Hierarchies('Branch')/Subsets('Default')"
			},
			"Selected":
			{
				"@id":"Dimensions('Branch')/Hierarchies('Branch')/Elements('TOTAL_BRANCH')"
			}
		}
	],
	"SuppressEmptyColumns":false,
	"SuppressEmptyRows":false,
	"FormatString":"0.#########"
}